styleysdk/__init__.py
styleysdk/deployments/__init__.py
styleysdk/deployments/deployments.py
styleysdk/deployments/model.py
styleysdk/deployments/test_deployments.py
styleysdk/models/__init__.py
styleysdk/models/model.py
styleysdk/models/models.py
styleysdk/models/test_models.py
styleysdk/shared/__init__.py
styleysdk/shared/client/__init__.py
styleysdk/shared/client/client.py
styleysdk/tests/__init__.py
styleysdk-0.1.3.dist-info/METADATA
styleysdk-0.1.3.dist-info/WHEEL
styleysdk-0.1.3.dist-info/RECORD
